Metadata-Version: 1.1
Name: pyelements
Version: 0.0.1
Summary: Tools for running experiments fast.
Home-page: http://github.com/danijar/elements
Author: UNKNOWN
Author-email: UNKNOWN
License: UNKNOWN
Platform: UNKNOWN
Classifier: Programming Language :: Python :: 3
Classifier: Topic :: Scientific/Engineering :: Visualization
Classifier: License :: OSI Approved :: Apache Software License
